django_logging_handlers/__init__.py
django_logging_handlers/handlers.py
django_logging_handlers/utils.py
django_logging_handlers-0.1.2.dist-info/LICENSE
django_logging_handlers-0.1.2.dist-info/METADATA
django_logging_handlers-0.1.2.dist-info/WHEEL
django_logging_handlers-0.1.2.dist-info/RECORD
