Metadata-Version: 2.1
Name: django-logging-handlers
Version: 0.1.2
Summary: Logging utility for Django
License: MIT
Author: Adrijan Bjedov
Author-email: adrijan.bjedov@gmail.com
Requires-Python: >=3.8,<4
Classifier: License :: OSI Approved :: MIT License
Classifier: Programming Language :: Python :: 3
Classifier: Programming Language :: Python :: 3.8
Classifier: Programming Language :: Python :: 3.9
Classifier: Programming Language :: Python :: 3.10
Classifier: Programming Language :: Python :: 3.11
Classifier: Programming Language :: Python :: 3.12
Requires-Dist: django (>=2)
Requires-Dist: requests
